displaylang/__init__.py
displaylang/allow.py
displaylang/build.py
displaylang/builtins.py
displaylang/depth.py
displaylang/evaluate.py
displaylang/exceptions.py
displaylang/visit.py
displaylang-0.24.1.dist-info/LICENSE
displaylang-0.24.1.dist-info/METADATA
displaylang-0.24.1.dist-info/NOTICE
displaylang-0.24.1.dist-info/WHEEL
displaylang-0.24.1.dist-info/top_level.txt
displaylang-0.24.1.dist-info/RECORD
