Metadata-Version: 2.1
Name: displaylang
Version: 0.24.1
Summary: Just enough Python to write displays
Home-page: https://github.com/proofscape/displaylang
License: Apache 2.0
Classifier: License :: OSI Approved :: Apache Software License
Classifier: Programming Language :: Python :: 3
License-File: LICENSE
License-File: NOTICE
Requires-Dist: pfsc-util >=0.22.8
Requires-Dist: typeguard ==2.13.3
Provides-Extra: dev
Requires-Dist: pytest ; extra == 'dev'
Requires-Dist: build ; extra == 'dev'
Requires-Dist: twine ; extra == 'dev'
Requires-Dist: invoke ; extra == 'dev'
